mat3ra/__init__.py
mat3ra/parsers/__init__.py
mat3ra_parsers-2024.3.21.post4.dist-info/LICENSE.md
mat3ra_parsers-2024.3.21.post4.dist-info/METADATA
mat3ra_parsers-2024.3.21.post4.dist-info/WHEEL
mat3ra_parsers-2024.3.21.post4.dist-info/top_level.txt
mat3ra_parsers-2024.3.21.post4.dist-info/RECORD
