Metadata-Version: 2.1
Name: mat3ra-parsers
Version: 2024.3.21.post4
Summary: Parsers.
Author-email: "Exabyte Inc." <info@mat3ra.com>
License: # LICENSE
Classifier: Programming Language :: Python
Classifier: Programming Language :: Python :: 3
Classifier: Development Status :: 3 - Alpha
Classifier: Topic :: Software Development
Requires-Python: >=3.8
License-File: LICENSE.md
Requires-Dist: numpy
Provides-Extra: all
Requires-Dist: mat3ra-parsers[tests] ; extra == 'all'
Provides-Extra: tests
Requires-Dist: coverage[toml] >=5.3 ; extra == 'tests'
Requires-Dist: pre-commit ; extra == 'tests'
Requires-Dist: black ; extra == 'tests'
Requires-Dist: ruff ; extra == 'tests'
Requires-Dist: isort ; extra == 'tests'
Requires-Dist: mypy ; extra == 'tests'
Requires-Dist: pip-tools ; extra == 'tests'
